xlreport/__init__.py
xlreport/xlreport.py
xlreport-0.0.7.dist-info/METADATA
xlreport-0.0.7.dist-info/WHEEL
xlreport-0.0.7.dist-info/RECORD
