Metadata-Version: 2.4
Name: xlreport
Version: 0.0.7
Summary: xlreport – Easy Excel Export for Python objects
Project-URL: Homepage, https://github.com/ts-kontakt/xlreport
Author-email: Tomasz Sługocki <ts.kontakt@gmail.com>
License-Expression: MIT
Classifier: Operating System :: OS Independent
Classifier: Programming Language :: Python :: 3
Requires-Python: >=3.1
Requires-Dist: xlsxwriter
